financebuddy_parsers/__init__.py
financebuddy_parsers/configs/parser_argenta-be_xlsx_config.json
financebuddy_parsers/configs/parser_bnp-be_csv_config.json
financebuddy_parsers/configs/parser_ing-be_csv_config.json
financebuddy_parsers/configs/parser_keytrade_csv_config.json
financebuddy_parsers/configs/parser_revolut_csv_config.json
financebuddy_parsers/samples/sample_argenta-be_xlsx_nl.xlsx
financebuddy_parsers/samples/sample_bnp-be_csv_nl.csv
financebuddy_parsers/samples/sample_ing-be_csv_en.csv
financebuddy_parsers/samples/sample_ing-be_csv_fr.csv
financebuddy_parsers/samples/sample_keytrade_csv_en.csv
financebuddy_parsers/samples/sample_revolut_csv_it.csv
financebuddy_parsers-0.6.0.dist-info/METADATA
financebuddy_parsers-0.6.0.dist-info/WHEEL
financebuddy_parsers-0.6.0.dist-info/licenses/LICENSE.md
financebuddy_parsers-0.6.0.dist-info/RECORD
