Metadata-Version: 2.3
Name: financebuddy-parsers
Version: 0.6.0
Summary: FinanceBuddy parsers repository.
Author-email: Cedric Duriau <duriau.cedric@live.be>
License-File: LICENSE.md
Requires-Python: >=3.12
Provides-Extra: dev
Requires-Dist: pip-tools>=6.12.0; extra == 'dev'
Requires-Dist: ruff>=0.0.290; extra == 'dev'
